llmutilsdougc333/__init__.py
llmutilsdougc333/main.py
llmutilsdougc333-0.1.2.dist-info/LICENSE
llmutilsdougc333-0.1.2.dist-info/METADATA
llmutilsdougc333-0.1.2.dist-info/WHEEL
llmutilsdougc333-0.1.2.dist-info/entry_points.txt
llmutilsdougc333-0.1.2.dist-info/top_level.txt
llmutilsdougc333-0.1.2.dist-info/RECORD
