Metadata-Version: 2.1
Name: llmutilsdougc333
Version: 0.1.2
Summary: A sample Python project
Home-page: https://github.com/dougc333/test_python/llmutils
Author: dc
Author-email: dougchang25@gmail.com
Classifier: Programming Language :: Python :: 3
Classifier: License :: OSI Approved :: MIT License
Classifier: Operating System :: OS Independent
Requires-Python: >=3.8
License-File: LICENSE
Requires-Dist: torch
